mcpbytes_lambda/stdio/__init__.py
mcpbytes_lambda/stdio/adapter.py
mcpbytes_lambda_stdio-0.1.3.dist-info/METADATA
mcpbytes_lambda_stdio-0.1.3.dist-info/WHEEL
mcpbytes_lambda_stdio-0.1.3.dist-info/RECORD
