Metadata-Version: 2.4
Name: mcpbytes-lambda-stdio
Version: 0.1.3
Summary: Stdio transport adapter for mcpbytes-lambda MCP servers
Project-URL: Homepage, https://mcpbytes.com/
Project-URL: Repository, https://github.com/MCPBytes/mcpbytes-lambda
Project-URL: Issues, https://github.com/MCPBytes/mcpbytes-lambda/issues
Project-URL: Documentation, https://github.com/MCPBytes/mcpbytes-lambda#readme
Author-email: "MCPBytes.com" <hello@mcpbytes.com>
License-Expression: Apache-2.0
Keywords: mcp,model-context-protocol,stdio,transport
Classifier: Development Status :: 4 - Beta
Classifier: Intended Audience :: Developers
Classifier: License :: OSI Approved :: Apache Software License
Classifier: Programming Language :: Python :: 3
Classifier: Programming Language :: Python :: 3.12
Classifier: Topic :: Internet :: WWW/HTTP :: HTTP Servers
Classifier: Topic :: Software Development :: Libraries :: Application Frameworks
Classifier: Topic :: Software Development :: Libraries :: Python Modules
Requires-Python: >=3.12
Requires-Dist: mcpbytes-lambda-core>=0.2.1
